PyCharacterAI/__init__.py
PyCharacterAI/client.py
PyCharacterAI/exceptions.py
PyCharacterAI/requester.py
PyCharacterAI/methods/__init__.py
PyCharacterAI/methods/account.py
PyCharacterAI/methods/character.py
PyCharacterAI/methods/chat.py
PyCharacterAI/methods/user.py
PyCharacterAI/methods/utils.py
PyCharacterAI/types/__init__.py
PyCharacterAI/types/base.py
PyCharacterAI/types/character.py
PyCharacterAI/types/chat.py
PyCharacterAI/types/media.py
PyCharacterAI/types/message.py
PyCharacterAI/types/user.py
pycharacterai-2.2.431.dist-info/METADATA
pycharacterai-2.2.431.dist-info/WHEEL
pycharacterai-2.2.431.dist-info/licenses/LICENSE
pycharacterai-2.2.431.dist-info/RECORD
