Metadata-Version: 2.4
Name: PyCharacterAI
Version: 2.2.431
Summary: An unofficial asynchronous api wrapper for Character AI.
Project-URL: Homepage, https://github.com/Xtr4F/PyCharacterAI
Project-URL: Documentation, https://github.com/Xtr4F/PyCharacterAI/blob/main/docs/welcome.md
Project-URL: Repository, https://github.com/Xtr4F/PyCharacterAI.git
Project-URL: Issues, https://github.com/Xtr4F/PyCharacterAI/issues
Author-email: XtraF <igoromarov15@gmail.com>
Maintainer-email: XtraF <igoromarov15@gmail.com>
License-Expression: MIT
License-File: LICENSE
Keywords: ai,api,asyncio,cai,character,characterai,wrapper
Classifier: License :: OSI Approved :: MIT License
Classifier: Programming Language :: Python :: 3.8
Classifier: Programming Language :: Python :: 3.9
Classifier: Programming Language :: Python :: 3.10
Classifier: Programming Language :: Python :: 3.11
Classifier: Programming Language :: Python :: 3.12
Classifier: Programming Language :: Python :: 3.13
Requires-Python: >=3.10
Requires-Dist: curl-cffi>=0.11.1
